testforeman/__init__.py
testforeman/server.py
testforeman-0.0.1.dist-info/LICENSE
testforeman-0.0.1.dist-info/METADATA
testforeman-0.0.1.dist-info/WHEEL
testforeman-0.0.1.dist-info/entry_points.txt
testforeman-0.0.1.dist-info/top_level.txt
testforeman-0.0.1.dist-info/RECORD
